setup.py
txTwitterStream.egg-info/PKG-INFO
txTwitterStream.egg-info/SOURCES.txt
txTwitterStream.egg-info/dependency_links.txt
txTwitterStream.egg-info/not-zip-safe
txTwitterStream.egg-info/requires.txt
txTwitterStream.egg-info/top_level.txt
txtwitterstream/__init__.py
txtwitterstream/client.py
txtwitterstream/util.py
txtwitterstream/test/__init__.py
txtwitterstream/test/test_client.py