Metadata-Version: 1.0
Name: txTwitterStream
Version: 0.0.3
Summary: A fork of Alexandre Fiori's TwistedTwitterStream Twitter client library for the Twitter Streaming API
Home-page: http://github.com/wadey/txtwitterstream
Author: Wade Simmons
Author-email: wade@wades.im
License: BSD
Platform: UNKNOWN
Classifier: Development Status :: 4 - Beta
Classifier: License :: OSI Approved :: BSD License
Classifier: License :: DFSG approved
Classifier: Intended Audience :: Developers
Classifier: Operating System :: OS Independent
Classifier: Natural Language :: English
Classifier: Programming Language :: Python
Classifier: Programming Language :: Python :: 2
Classifier: Programming Language :: Python :: 2.5
Classifier: Programming Language :: Python :: 2.6
Classifier: Topic :: Utilities
Classifier: Topic :: Software Development :: Libraries
